name_generator_nicomp/NameGenerator.py
name_generator_nicomp/__init__.py
name_generator_nicomp/adjectives.txt
name_generator_nicomp/adjectives_master.txt
name_generator_nicomp/nouns.txt
name_generator_nicomp/nouns_master.txt
name_generator_nicomp/utilities.py
name_generator_nicomp-1.0.10.dist-info/METADATA
name_generator_nicomp-1.0.10.dist-info/WHEEL
name_generator_nicomp-1.0.10.dist-info/licenses/LICENSE
name_generator_nicomp-1.0.10.dist-info/RECORD
